uniserve.cpython-310-x86_64-linux-gnu.so
uniserve.pyi
uniserve-0.0.5.dist-info/METADATA
uniserve-0.0.5.dist-info/WHEEL
uniserve-0.0.5.dist-info/entry_points.txt
uniserve-0.0.5.dist-info/top_level.txt
uniserve-0.0.5.dist-info/RECORD
uniserve-0.0.5.dist-info/licenses/LICENSE
