Metadata-Version: 2.4
Name: uniserve
Version: 0.0.5
Summary: model serving frame work
Author-email: Yaqiang Sun <sunyaking@163.com>
License: GPL-3.0
Requires-Python: <3.14,>=3.10
License-File: LICENSE
Requires-Dist: litserve>=0.2.16
Dynamic: license-file
